llama_benchy/__init__.py
llama_benchy/__main__.py
llama_benchy/_version.py
llama_benchy-0.1.2.dist-info/METADATA
llama_benchy-0.1.2.dist-info/WHEEL
llama_benchy-0.1.2.dist-info/entry_points.txt
llama_benchy-0.1.2.dist-info/licenses/LICENSE
llama_benchy-0.1.2.dist-info/RECORD
