Metadata-Version: 2.4
Name: llama-benchy
Version: 0.1.2
Summary: llama-bench style benchmarking tool for all OpenAI-compatible LLM endpoints
Project-URL: Homepage, https://github.com/eugr/llama-benchy
Project-URL: Bug Tracker, https://github.com/eugr/llama-benchy/issues
Author: eugr
License: MIT License
License-File: LICENSE
Classifier: Intended Audience :: Science/Research
Classifier: License :: OSI Approved :: MIT License
Classifier: Operating System :: OS Independent
Classifier: Programming Language :: Python :: 3
Classifier: Programming Language :: Python :: 3.10
Classifier: Programming Language :: Python :: 3.11
Classifier: Programming Language :: Python :: 3.12
Classifier: Topic :: Scientific/Engineering :: Artificial Intelligence
Requires-Python: >=3.10
Requires-Dist: aiohttp
Requires-Dist: asyncio
Requires-Dist: numpy
Requires-Dist: openai
Requires-Dist: requests
Requires-Dist: tabulate
Requires-Dist: transformers
